azure/mgmt/cdn/__init__.py
azure/mgmt/cdn/_cdn_management_client.py
azure/mgmt/cdn/_configuration.py
azure/mgmt/cdn/_patch.py
azure/mgmt/cdn/_serialization.py
azure/mgmt/cdn/_vendor.py
azure/mgmt/cdn/_version.py
azure/mgmt/cdn/py.typed
azure/mgmt/cdn/aio/__init__.py
azure/mgmt/cdn/aio/_cdn_management_client.py
azure/mgmt/cdn/aio/_configuration.py
azure/mgmt/cdn/aio/_patch.py
azure/mgmt/cdn/aio/_vendor.py
azure/mgmt/cdn/aio/operations/__init__.py
azure/mgmt/cdn/aio/operations/_afd_custom_domains_operations.py
azure/mgmt/cdn/aio/operations/_afd_endpoints_operations.py
azure/mgmt/cdn/aio/operations/_afd_origin_groups_operations.py
azure/mgmt/cdn/aio/operations/_afd_origins_operations.py
azure/mgmt/cdn/aio/operations/_afd_profiles_operations.py
azure/mgmt/cdn/aio/operations/_cdn_management_client_operations.py
azure/mgmt/cdn/aio/operations/_custom_domains_operations.py
azure/mgmt/cdn/aio/operations/_edge_nodes_operations.py
azure/mgmt/cdn/aio/operations/_endpoints_operations.py
azure/mgmt/cdn/aio/operations/_log_analytics_operations.py
azure/mgmt/cdn/aio/operations/_managed_rule_sets_operations.py
azure/mgmt/cdn/aio/operations/_operations.py
azure/mgmt/cdn/aio/operations/_origin_groups_operations.py
azure/mgmt/cdn/aio/operations/_origins_operations.py
azure/mgmt/cdn/aio/operations/_patch.py
azure/mgmt/cdn/aio/operations/_policies_operations.py
azure/mgmt/cdn/aio/operations/_profiles_operations.py
azure/mgmt/cdn/aio/operations/_resource_usage_operations.py
azure/mgmt/cdn/aio/operations/_routes_operations.py
azure/mgmt/cdn/aio/operations/_rule_sets_operations.py
azure/mgmt/cdn/aio/operations/_rules_operations.py
azure/mgmt/cdn/aio/operations/_secrets_operations.py
azure/mgmt/cdn/aio/operations/_security_policies_operations.py
azure/mgmt/cdn/models/__init__.py
azure/mgmt/cdn/models/_cdn_management_client_enums.py
azure/mgmt/cdn/models/_models_py3.py
azure/mgmt/cdn/models/_patch.py
azure/mgmt/cdn/operations/__init__.py
azure_mgmt_cdn-13.1.1.dist-info/LICENSE
azure_mgmt_cdn-13.1.1.dist-info/METADATA
azure_mgmt_cdn-13.1.1.dist-info/WHEEL
azure_mgmt_cdn-13.1.1.dist-info/top_level.txt
azure_mgmt_cdn-13.1.1.dist-info/RECORD
